mono_client/__init__.py
mono_client/client.py
mono_client-0.3.1.dist-info/METADATA
mono_client-0.3.1.dist-info/WHEEL
mono_client-0.3.1.dist-info/RECORD
