Metadata-Version: 2.1
Name: mono_client
Version: 0.3.1
Summary: Access high-quality financial data and perform direct bank payments with mono.co
Project-URL: Homepage, https://github.com/Abdoulrasheed/mono_client
Project-URL: Bug Tracker, https://github.com/Abdoulrasheed/mono_client/issues
Author-email: Abdulrasheed Ibrahim <hello@abdull.dev>
License: Copyright (c) 2018 The Python Packaging Authority
Classifier: License :: OSI Approved :: MIT License
Classifier: Operating System :: OS Independent
Classifier: Programming Language :: Python :: 3
Requires-Python: >=3.6
